kowalski/__init__.py
kowalski/neural_collapse.py
kowalski/power_law.py
kowalski/rankme.py
kowalski/utils.py
kowalski-0.0.2.dist-info/LICENSE
kowalski-0.0.2.dist-info/METADATA
kowalski-0.0.2.dist-info/WHEEL
kowalski-0.0.2.dist-info/top_level.txt
kowalski-0.0.2.dist-info/RECORD
