Metadata-Version: 2.2
Name: kowalski
Version: 0.0.2
Summary: A suite of standard metrics for assessing learned feature representations, in PyTorch.
Author-email: Viet Anh Khoa Tran <v.tran@fz-juelich.de>
License: MIT
Requires-Python: >=3.10
License-File: LICENSE
Requires-Dist: torch
Requires-Dist: einops
Requires-Dist: matplotlib
Requires-Dist: jaxtyping
